klarf_reader/klarf.py
klarf_reader/models/klarf_content.py
klarf_reader/readers/klarf_file_reader.py
klarf_reader/utils/klarf_convert.py
klarf_reader-0.4.3.dist-info/LICENSE.txt
klarf_reader-0.4.3.dist-info/METADATA
klarf_reader-0.4.3.dist-info/WHEEL
klarf_reader-0.4.3.dist-info/top_level.txt
klarf_reader-0.4.3.dist-info/RECORD
