Metadata-Version: 2.1
Name: klarf-reader
Version: 0.4.3
Summary: A project to parse klarf file and get klarf content as dataclass
Home-page: https://github.com/Impro02/klarf_reader
Download-URL: https://github.com/Impro02/klarf_reader/archive/refs/tags/0.4.3.tar.gz
Author: Maxime MARTIN
Author-email: maxime.martin02@hotmail.fr
License: MIT
Classifier: Development Status :: 3 - Alpha
Classifier: Intended Audience :: Developers
Classifier: License :: OSI Approved :: MIT License
Classifier: Programming Language :: Python :: 3
License-File: LICENSE.txt
Requires-Dist: numba
